commands/__init__.py
commands/testing.py
commands/utils.py
datagrowth/__init__.py
datagrowth/admin.py
datagrowth/apps.py
datagrowth/exceptions.py
datagrowth/settings.py
datagrowth/version.py
datagrowth/configuration/__init__.py
datagrowth/configuration/configs.py
datagrowth/configuration/fields.py
datagrowth/configuration/serializers.py
datagrowth/configuration/types.py
datagrowth/datatypes/__init__.py
datagrowth/datatypes/admin.py
datagrowth/datatypes/storage.py
datagrowth/datatypes/types.py
datagrowth/datatypes/views.py
datagrowth/datatypes/annotations/__init__.py
datagrowth/datatypes/annotations/admin.py
datagrowth/datatypes/annotations/base.py
datagrowth/datatypes/annotations/views.py
datagrowth/datatypes/datasets/__init__.py
datagrowth/datatypes/datasets/admin.py
datagrowth/datatypes/datasets/constants.py
datagrowth/datatypes/datasets/db/__init__.py
datagrowth/datatypes/datasets/db/dataset.py
datagrowth/datatypes/documents/__init__.py
datagrowth/datatypes/documents/admin.py
datagrowth/datatypes/documents/db/__init__.py
datagrowth/datatypes/documents/db/collection.py
datagrowth/datatypes/documents/db/document.py
datagrowth/datatypes/documents/db/growth.py
datagrowth/datatypes/documents/db/version.py
datagrowth/datatypes/documents/tasks/__init__.py
datagrowth/datatypes/documents/tasks/base.py
datagrowth/datatypes/documents/tasks/collection.py
datagrowth/datatypes/documents/tasks/dataset_version.py
datagrowth/datatypes/documents/tasks/document.py
datagrowth/datatypes/documents/views/__init__.py
datagrowth/datatypes/documents/views/collection.py
datagrowth/datatypes/documents/views/content.py
datagrowth/datatypes/documents/views/document.py
datagrowth/management/__init__.py
datagrowth/management/base.py
datagrowth/management/commands/__init__.py
datagrowth/management/commands/copy_dataset.py
datagrowth/management/commands/dump_dataset.py
datagrowth/management/commands/dump_resource.py
datagrowth/management/commands/grow_dataset.py
datagrowth-0.20.6.dist-info/licenses/LICENSE
datagrowth-0.20.6.dist-info/METADATA
datagrowth-0.20.6.dist-info/WHEEL
datagrowth-0.20.6.dist-info/top_level.txt
datagrowth-0.20.6.dist-info/RECORD
