Metadata-Version: 2.4
Name: datagrowth
Version: 0.20.6
Summary: Data engineering tools to create data mash ups using Django
Author-email: Fako Berkers <email@fakoberkers.nl>
Maintainer-email: Fako Berkers <email@fakoberkers.nl>
License-Expression: LGPL-3.0-only
Project-URL: Homepage, https://github.com/fako/datagrowth
Project-URL: Bug Tracker, https://github.com/fako/datagrowth/issues
Classifier: Programming Language :: Python :: 3.9
Classifier: Programming Language :: Python :: 3.10
Classifier: Programming Language :: Python :: 3.11
Classifier: Programming Language :: Python :: 3.12
Classifier: Programming Language :: Python :: 3.13
Classifier: Framework :: Django :: 4.2
Classifier: Framework :: Django :: 5.2
Classifier: Operating System :: OS Independent
Requires-Python: ~=3.9
License-File: LICENSE
Requires-Dist: Django>=4.2
Requires-Dist: celery
Requires-Dist: jsonschema>=4.20.0
Requires-Dist: lxml
Requires-Dist: beautifulsoup4
Requires-Dist: urlobject
Requires-Dist: requests
Requires-Dist: Pillow>=11
Requires-Dist: tqdm
Dynamic: license-file
